Workbook

Sheet Petunjuk
B2: Daftar Konfirmasi Kebutuhan Sistem — Balans Nutrition
B3: Versi 0.1 · 14 Oktober 2026
B5: Tujuan | C5: Mengumpulkan jawaban dan persetujuan Balans atas hal-hal yang perlu dipastikan sebelum sistem dirancang dan dibangun.
B6: Sheet 'Pertanyaan' | C6: Pertanyaan yang perlu dijawab Balans. Mohon prioritaskan pertanyaan dengan batas waktu paling dekat dan prioritas Tinggi.
B7: Sheet 'Konfirmasi' | C7: Hal-hal yang sudah kami pahami dari pembahasan sebelumnya. Mohon pilih Setuju / Tidak Setuju / Perlu Diskusi untuk setiap baris.
B8: Sheet 'Validasi Akuntansi' | C8: Usulan pencatatan jurnal otomatis untuk setiap jenis transaksi. Mohon direview oleh tim Finance & Accounting Balans.
B9: Sheet 'Ringkasan' | C9: Rekap otomatis jumlah jawaban dan persetujuan. Tidak perlu diisi.
B10: Kolom yang diisi Balans | C10: Hanya kolom berwarna kuning. Kolom lain sudah kami isi.
B11: Pilihan Status | C11: Terbuka = belum dijawab · Terjawab = jawaban sudah final · Perlu Diskusi = butuh pembahasan lebih lanjut.
B12: Lampiran | C12: Jika jawaban berupa dokumen (contoh price list, PKS, laporan rekonsiliasi, COA), sebutkan nama file di kolom Jawaban dan kirimkan bersama file ini.
B14: Contoh pengisian
B15: Kolom | C15: Contoh isian
B16: ID | C16: P-03
B17: Pertanyaan | C17: Ada berapa model harga yang berlaku saat ini, dan bagaimana aturannya?
B18: Jawaban Balans | C18: Ada 4 price list: MT, marketplace, reseller, karyawan (diskon 20% dari harga marketplace). Harga promo diatur per periode. Lampiran: PriceList_Okt2026.xlsx
B19: PIC Balans | C19: Nama (Divisi)
B20: Tanggal Dijawab | C20: 20/11/2026
B21: Status | C21: Terjawab
B22: Contoh di atas hanya ilustrasi format pengisian.

Sheet Pertanyaan
A1: No | B1: ID | C1: Area | D1: Pertanyaan | E1: Konteks | F1: Opsi / Usulan | G1: Mengapa Penting | H1: Batas Waktu | I1: Prioritas | J1: Jawaban Balans | K1: PIC Balans | L1: Tanggal Dijawab | M1: Status
A2: 1 | B2: P-01 | C2: Gudang | D2: Apa arti "GM" pada "Gudang GM" dan "re-processing GM jadi FG"? | E2: Istilah ini muncul di catatan kebutuhan: "Raw Material, Gudang GM" dan alur retur "PO ke maklon untuk re-processing GM jadi FG". | F2: Kemungkinan: Raw Material atau Good Material. Mohon konfirmasi kepanjangannya dan jenis barang yang disimpan di gudang tersebut. | G2: Menentukan struktur gudang dan jenis stok yang dicatat di gudang tersebut. | H2: 27 Nov 2026 | I2: Tinggi | J2: asumsi kita dulu saja untuk proposed solution terbaik | M2: Terbuka
A3: 2 | B3: P-02 | C3: Konsinyasi | D3: Bagaimana cara menghitung rekonsiliasi konsinyasi saat ini, dan bagaimana penanganan barang hilang/rusak di lokasi partner? | E3: Stok konsinyasi tetap milik Balans sampai terjual, dan ditagihkan setiap bulan berdasarkan hasil rekonsiliasi. | F3: Usulan rumus: stok awal + kiriman − sisa stok fisik = terjual. Barang hilang/rusak: ditagihkan ke partner, ditanggung Balans, atau sesuai PKS masing-masing partner. Mohon lampirkan contoh laporan rekonsiliasi dan PKS. | G3: Menentukan format rekonsiliasi, dasar penagihan konsinyasi, dan pencatatan selisih stok. | H3: 27 Nov 2026 | I3: Tinggi | J3: asumsi kita dulu saja untuk proposed solution terbaik | M3: Terbuka
A4: 3 | B4: P-03 | C4: Harga | D4: Ada berapa model harga yang berlaku saat ini, dan bagaimana aturannya? | E4: Catatan kebutuhan menyebut "ada model beberapa harga produk dan tidak tetap". | F4: Contoh model: harga per channel (MT, marketplace, website, reseller, karyawan), harga per partner, harga promo periode tertentu, harga berdasarkan jumlah pembelian. Mohon lampirkan price list yang berlaku. | G4: Menentukan struktur daftar harga dan aturan diskon. | H4: 27 Nov 2026 | I4: Tinggi | J4: asumsi kita dulu saja untuk proposed solution terbaik | M4: Terbuka
A5: 4 | B5: P-04 | C5: Finance & Accounting | D5: Mohon validasi usulan pencatatan akuntansi di sheet 'Validasi Akuntansi', dan lampirkan Chart of Accounts (COA) yang berlaku jika ada. | E5: Setiap transaksi operasional (pembelian, penjualan, konsinyasi, retur, pemakaian internal) akan otomatis menghasilkan jurnal. | F5: Tim Finance & Accounting Balans mengisi Setuju / Tidak Setuju / Perlu Diskusi untuk setiap baris di sheet 'Validasi Akuntansi'. | G5: Menjadi dasar pengaturan jurnal otomatis dan COA. | H5: 27 Nov 2026 | I5: Tinggi | J5: asumsi kita dulu saja untuk proposed solution terbaik | M5: Terbuka
A6: 5 | B6: P-05 | C6: Vending Machine | D6: Merek/vendor vending machine apa yang dipakai? Apakah vendor menyediakan API/webhook? Berapa jumlah mesin saat ini dan rencananya? | E6: Integrasi pembayaran (Midtrans) dan integrasi perangkat mesin adalah dua hal yang berbeda. Integrasi perangkat bergantung pada dokumentasi API dari vendor, sehingga vendor perlu dihubungi sejak awal. | F6: Mohon berikan kontak vendor dan dokumentasi API jika ada. | G6: Menentukan apakah transaksi dan stok mesin bisa tercatat otomatis. Jika tidak ada API, pencatatan memakai data transaksi Midtrans dan input refill manual. | H6: 27 Nov 2026 | I6: Tinggi | J6: asumsi kita dulu saja untuk proposed solution terbaik | M6: Terbuka
A7: 6 | B7: P-06 | C7: Finance & Accounting | D7: Selain PPN, pajak apa saja yang saat ini dipotong atau dibayar Balans, dan apakah perlu dicatat di sistem? | E7: Balans berstatus NON-PKP sehingga tidak memungut PPN. Namun kewajiban pajak lain bisa tetap berlaku, misalnya pemotongan PPh atas fee endorsement atau jasa. | F7: Contoh: PPh 21 (karyawan, endorser perorangan), PPh 23 (jasa dari badan usaha), PPh Final atas omzet. Mohon sebutkan yang berlaku dan siapa yang mengurus pelaporannya saat ini. | G7: Menentukan apakah sistem perlu mencatat potongan pajak dan utang pajak. | H7: 27 Nov 2026 | I7: Tinggi | J7: asumsi kita dulu saja untuk proposed solution terbaik | M7: Terbuka
A8: 7 | B8: P-07 | C8: Procurement | D8: Siapa saja approver PO, dan berapa batas nominal untuk setiap level approval? | E8: Alur pembelian mengikuti pola standar: Purchase Request (opsional) → PO → approval berjenjang berdasarkan nominal (lihat K-06). | F8: Contoh: PO sampai Rp10 juta disetujui Head Finance & Accounting; PO di atas Rp10 juta disetujui Direksi. | G8: Pengaturan approval PO. | H8: 27 Nov 2026 | I8: Sedang | J8: asumsi kita dulu saja untuk proposed solution terbaik | M8: Terbuka
A9: 8 | B9: P-08 | C9: Gudang | D9: Berapa gudang fisik yang ada saat ini, dan lokasi apa saja di dalam masing-masing gudang? | E9: Sistem mendukung lebih dari satu gudang fisik (lihat K-07). | F9: Mohon isi daftar: nama gudang fisik, alamat, dan lokasi di dalamnya (Inbound, Finished Goods, Petty Stock, Retur, Raw Material/GM). | G9: Pengaturan awal gudang dan pemindahan saldo stok awal. | H9: 27 Nov 2026 | I9: Sedang | J9: asumsi kita dulu saja untuk proposed solution terbaik | M9: Terbuka
A10: 9 | B10: P-09 | C10: Retur | D10: Apakah barang retur diperiksa (QC) terlebih dahulu sebelum diputuskan tindak lanjutnya? Siapa yang memutuskan? | E10: Barang retur bisa di-repacking internal atau di-re-processing ke maklon. | F10: Usulan alur: terima retur → pemeriksaan → keputusan (kembali ke stok / repacking / re-processing / dimusnahkan) dengan approval. Mohon konfirmasi juga apakah ada opsi pemusnahan. | G10: Menentukan alur status barang di Gudang Retur dan pencatatannya. | H10: 27 Nov 2026 | I10: Sedang | J10: asumsi kita dulu saja untuk proposed solution terbaik | M10: Terbuka
A11: 10 | B11: P-10 | C11: Migrasi Data | D11: Data apa saja yang perlu dipindahkan ke sistem baru? Apakah transaksi historis juga perlu dipindahkan? | E11: Usulan: hanya data master (produk, customer, supplier, partner), saldo stok per batch, dan saldo awal akuntansi. | F11: A) Data master + saldo awal saja (disarankan). B) Ditambah transaksi historis untuk periode tertentu (mohon sebutkan periodenya). | G11: Menentukan besarnya pekerjaan pemindahan data dan jadwal peralihan ke sistem baru. | H11: 27 Nov 2026 | I11: Sedang | J11: asumsi kita dulu saja untuk proposed solution terbaik | M11: Terbuka
A12: 11 | B12: P-11 | C12: Finance & Accounting | D12: Apakah mesin vending perlu dicatat sebagai aset tetap beserta penyusutannya di sistem? | E12: Mesin vending milik Balans (lihat K-05). | F12: A) Ya, sistem mencatat aset tetap dan penyusutan. B) Tidak, dicatat di luar sistem. | G12: Jika A, lingkup fitur Finance & Accounting bertambah. | H12: 27 Nov 2026 | I12: Sedang | J12: asumsi kita dulu saja untuk proposed solution terbaik | M12: Terbuka
A13: 12 | B13: P-12 | C13: Vending Machine | D13: Siapa yang melakukan refill mesin: tim Balans atau partner di lokasi? | E13: Stok di dalam mesin tetap milik Balans sampai terjual. | F13: A) Tim Balans. B) Partner di lokasi. C) Tergantung lokasi. | G13: Menentukan alur pengisian stok mesin dan tanggung jawab atas selisih stok. | H13: 27 Nov 2026 | I13: Sedang | J13: partner dengan asumsi kita dulu saja untuk proposed solution terbaik | M13: Terbuka
... A23: 22 | B23: P-22 | C23: HRIS | D23: Lingkup HRIS yang dibutuhkan: hanya data karyawan, atau termasuk absensi, cuti, payroll, BPJS, dan PPh 21? | E23: Yang sudah tercakup: data karyawan, sample karyawan, dan diskon karyawan. | F23: A) Cukup yang sudah tercakup. B) HRIS lengkap. C) Memakai aplikasi HRIS terpisah yang dihubungkan ke Finance & Accounting. | G23: Menentukan lingkup fitur HRIS. | H23: 27 Sep 2027 | I23: Rendah | J23: Lingkup fitur HRIS lengkap sampai ke absensi. | M23: Terbuka
A24: 23 | B24: P-23 | C24: HRIS | D24: Berapa jumlah karyawan saat ini? | E24: Dibutuhkan untuk menilai kebutuhan HRIS. | G24: Membantu memilih opsi HRIS. | H24: 27 Sep 2027 | I24: Rendah | J24: anggap saja 50+ | M24: Terbuka

Sheet Konfirmasi
A1: No | B1: ID | C1: Topik | D1: Pernyataan | E1: Keterangan | F1: Setuju? | G1: Catatan Balans | H1: PIC Balans | I1: Tanggal
A2: 1 | B2: K-01 | C2: Batch & tanggal kedaluwarsa | D2: Setiap produk dicatat per batch beserta tanggal kedaluwarsanya di seluruh pergerakan stok. Batch dan tanggal kedaluwarsa wajib diisi saat barang diterima. | E2: Staf gudang perlu mencatat batch dan tanggal kedaluwarsa setiap kali menerima barang.
A3: 2 | B3: K-02 | C3: Pengambilan stok FEFO | D3: Sistem menyarankan pengambilan batch dengan tanggal kedaluwarsa terdekat terlebih dahulu (First Expired, First Out) saat menyiapkan pesanan dan memindahkan stok. | E3: Mengurangi risiko produk kedaluwarsa di gudang.
A4: 3 | B4: K-03 | C4: Metode HPP | D4: Persediaan dinilai dengan metode FIFO (First In, First Out). | E4: Menjadi dasar perhitungan HPP dan jurnal.
A5: 4 | B5: K-04 | C5: Status pajak | D5: Balans berstatus NON-PKP dan tidak berencana menjadi PKP. Invoice diterbitkan tanpa PPN, dan fitur PPN/e-Faktur tidak disediakan. | E5: Jika di kemudian hari Balans menjadi PKP, fitur pajak ditambahkan sebagai pengembangan terpisah.
A6: 5 | B6: K-05 | C6: Kepemilikan stok konsinyasi & vending | D6: Stok di lokasi konsinyasi dan di dalam vending machine tetap milik Balans sampai terjual. Mesin vending adalah milik Balans. | E6: Penjualan konsinyasi diakui saat rekonsiliasi; penjualan vending diakui saat transaksi di mesin.
A7: 6 | B7: K-06 | C7: Alur pembelian (procurement) | D7: Alur pembelian: Purchase Request dari divisi (opsional) → PO → approval berjenjang berdasarkan nominal → penerimaan barang → tagihan supplier → pencocokan PO, penerimaan, dan tagihan → pembayaran. | E7: Detail approver dan batas nominal ditanyakan di P-07.
A8: 7 | B8: K-07 | C8: Gudang & penerimaan barang | D8: Sistem mendukung lebih dari satu gudang fisik. Semua kedatangan barang (dari supplier, maklon, retur customer, dan tarikan dari lokasi konsinyasi) masuk ke Gudang Inbound terlebih dahulu. | E8: Daftar gudang fisik ditanyakan di P-08.
A9: 8 | B9: K-08 | C9: Raw Material & maklon | D9: Maklon bersifat full service: menyediakan bahan isi produk (formula/ingredients) dan memproduksi; biaya bahan isi termasuk harga jasa maklon. Raw Material yang dibeli Balans hanya packaging (Tube, Pouch, Roll Sachet), yang dikirim ke maklon dan tetap tercatat sebagai stok Balans sampai dipakai produksi. | E9: HPP produk = packaging + jasa maklon (termasuk bahan isi) + reject/waste.
A10: 9 | B10: K-09 | C10: Ongkir di website | D10: Cek ongkir di website memakai layanan Biteship, yang mencakup JNE, Gojek, Grab, dan kurir lainnya. | E10: Estimasi biaya langganan sekitar Rp149.000/bulan, ongkir dibayar sesuai tarif kurir. Akun Biteship atas nama Balans.
A11: 10 | B11: K-10 | C11: Modern Trade beli putus | D11: Untuk Modern Trade beli putus, invoice diterbitkan saat pembayaran dari toko dikonfirmasi, dan pembayaran langsung dicatat ke invoice tersebut. Proforma Invoice dipakai sebagai permintaan pembayaran. | E11: Tidak ada pencatatan uang muka penjualan terpisah.
A12: 11 | B12: K-11 | C12: Biaya operasional & kas kecil | D12: Biaya operasional di luar pembelian barang (fee endorsement, event, sewa, reimbursement) dan pengeluaran kas kecil dicatat di sistem dengan approval. | E12: Detail proses dan approver ditanyakan di P-13.
A13: 12 | B13: K-12 | C13: Koreksi jurnal | D13: Jurnal yang sudah diposting tidak bisa diedit atau dihapus. Koreksi dilakukan dengan jurnal balik (reversal), sehingga riwayat perubahan tetap tercatat. | E13: Menjaga jejak audit keuangan.
... A17: 16 | B17: K-16 | C17: Laporan akuntansi | D17: Laporan yang disediakan: Neraca Saldo (trial balance), Buku Besar detail, Neraca, Laba Rugi, Arus Kas, serta umur piutang dan utang. | E17: Pemisahan laba rugi per channel/divisi ditanyakan di P-14.

Sheet Validasi Akuntansi
A1: No | B1: ID | C1: Transaksi | D1: Debit | E1: Kredit | F1: Keterangan | G1: Setuju? | H1: Catatan Balans
A2: 1 | B2: A-01 | C2: Penerimaan barang/packaging dari supplier | D2: Persediaan | E2: Utang Usaha
A3: 2 | B3: A-02 | C3: Retur pembelian ke supplier | D3: Utang Usaha | E3: Persediaan | F3: Berdasarkan nota debit.
A4: 3 | B4: A-03 | C4: Penerimaan Finished Goods dari maklon | D4: Persediaan Finished Goods | E4: Persediaan Packaging + Utang Jasa Maklon | F4: Nilai Finished Goods = packaging + jasa maklon (termasuk bahan isi).
A5: 4 | B5: A-04 | C5: Reject/waste dari packaging dan hasil maklon | D5: HPP Finished Goods (menambah nilai per unit) | E5: — | F5: Biaya reject/waste dibebankan ke HPP produk yang baik.
A6: 5 | B6: A-05 | C6: Penjualan (Modern Trade beli putus, WA/IG, website, reseller) | D6: Piutang Usaha / Kas | E6: Penjualan | F6: Diskon dicatat sebagai potongan penjualan.
A7: 6 | B7: A-06 | C7: Pengakuan HPP atas penjualan | D7: HPP | E7: Persediaan Finished Goods | F7: Dinilai FIFO per batch.
A8: 7 | B8: A-07 | C8: Pengiriman barang konsinyasi ke partner | D8: Persediaan Konsinyasi | E8: Persediaan Finished Goods | F8: Belum diakui sebagai penjualan.
A9: 8 | B9: A-08 | C9: Hasil rekonsiliasi konsinyasi (barang terjual) | D9: Piutang Usaha | E9: Penjualan | F9: HPP barang terjual diakui pada saat ini.
A10: 9 | B10: A-09 | C10: Penjualan vending machine via Midtrans | D10: Piutang Midtrans | E10: Penjualan | F10: Saat dana cair: Debit Kas/Bank + Beban Fee, Kredit Piutang Midtrans.
A11: 10 | B11: A-10 | C11: Penjualan marketplace | D11: Piutang Marketplace | E11: Penjualan | F11: Saat dana cair: Debit Kas/Bank + Beban Fee Marketplace, Kredit Piutang Marketplace.
A12: 11 | B12: A-11 | C12: Pemakaian Finished Goods untuk marketing (endorsement, event, sample) | D12: Beban Marketing | E12: Persediaan Finished Goods | F12: Dinilai sebesar HPP.
A13: 12 | B13: A-12 | C13: Sample produk untuk karyawan | D13: Beban Karyawan / Operasional | E13: Persediaan Finished Goods | F13: Dinilai sebesar HPP.
A14: 13 | B14: A-13 | C14: Retur penjualan | D14: Retur Penjualan | E14: Piutang Usaha / Kas | F14: Barang masuk ke Persediaan Retur.
... A16: 15 | B16: A-15 | C16: Pembayaran biaya operasional (fee endorsement, event, sewa, reimbursement) | D16: Beban sesuai jenis biaya (mis. Beban Marketing, Beban Sewa) | E16: Kas/Bank atau Utang Usaha | F16: Akun beban mengikuti jenis biaya.
A17: 16 | B17: A-16 | C17: Pengisian kas kecil | D17: Kas Kecil | E17: Kas/Bank
A18: 17 | B18: A-17 | C18: Pengeluaran dari kas kecil | D18: Beban sesuai jenis biaya | E18: Kas Kecil | F18: Didukung bukti pengeluaran.
C20: Nama akun bersifat usulan dan akan disesuaikan dengan Chart of Accounts Balans.

Sheet Ringkasan
B2: Ringkasan Pertanyaan
B4: Batas Waktu | C4: Terbuka | D4: Terjawab | E4: Perlu Diskusi | F4: Total | G4: % Terjawab
B5: 27 Nov 2026 | C5: =COUNTIFS(Pertanyaan!$H$2:$H$24,$B5,Pertanyaan!$M$2:$M$24,C$4) -> 15 | D5: =COUNTIFS(Pertanyaan!$H$2:$H$24,$B5,Pertanyaan!$M$2:$M$24,D$4) -> 0 | E5: =COUNTIFS(Pertanyaan!$H$2:$H$24,$B5,Pertanyaan!$M$2:$M$24,E$4) -> 0 | F5: =COUNTIF(Pertanyaan!$H$2:$H$24,$B5) -> 15 | G5: =IF(F5=0,0,D5/F5) -> 0
B6: 29 Mar 2027 | C6: =COUNTIFS(Pertanyaan!$H$2:$H$24,$B6,Pertanyaan!$M$2:$M$24,C$4) -> 2 | D6: =COUNTIFS(Pertanyaan!$H$2:$H$24,$B6,Pertanyaan!$M$2:$M$24,D$4) -> 0 | E6: =COUNTIFS(Pertanyaan!$H$2:$H$24,$B6,Pertanyaan!$M$2:$M$24,E$4) -> 0 | F6: =COUNTIF(Pertanyaan!$H$2:$H$24,$B6) -> 2 | G6: =IF(F6=0,0,D6/F6) -> 0
B7: 31 Mei 2027 | C7: =COUNTIFS(Pertanyaan!$H$2:$H$24,$B7,Pertanyaan!$M$2:$M$24,C$4) -> 1 | D7: =COUNTIFS(Pertanyaan!$H$2:$H$24,$B7,Pertanyaan!$M$2:$M$24,D$4) -> 0 | E7: =COUNTIFS(Pertanyaan!$H$2:$H$24,$B7,Pertanyaan!$M$2:$M$24,E$4) -> 0 | F7: =COUNTIF(Pertanyaan!$H$2:$H$24,$B7) -> 1 | G7: =IF(F7=0,0,D7/F7) -> 0
B8: 27 Sep 2027 | C8: =COUNTIFS(Pertanyaan!$H$2:$H$24,$B8,Pertanyaan!$M$2:$M$24,C$4) -> 5 | D8: =COUNTIFS(Pertanyaan!$H$2:$H$24,$B8,Pertanyaan!$M$2:$M$24,D$4) -> 0 | E8: =COUNTIFS(Pertanyaan!$H$2:$H$24,$B8,Pertanyaan!$M$2:$M$24,E$4) -> 0 | F8: =COUNTIF(Pertanyaan!$H$2:$H$24,$B8) -> 5 | G8: =IF(F8=0,0,D8/F8) -> 0
B9: Total | C9: =SUM(C5:C8) -> 23 | D9: =SUM(D5:D8) -> 0 | E9: =SUM(E5:E8) -> 0 | F9: =SUM(F5:F8) -> 23 | G9: =IF(F9=0,0,D9/F9) -> 0
B12: Ringkasan Konfirmasi
B14: Status | C14: Jumlah
B15: Setuju | C15: =COUNTIF(Konfirmasi!$F$2:$F$17,B15) -> 0
B16: Tidak Setuju | C16: =COUNTIF(Konfirmasi!$F$2:$F$17,B16) -> 0
B17: Perlu Diskusi | C17: =COUNTIF(Konfirmasi!$F$2:$F$17,B17) -> 0
B18: Belum diisi | C18: =COUNTA(Konfirmasi!$B$2:$B$17)-SUM(C15:C17) -> 16
B19: Total | C19: =COUNTA(Konfirmasi!$B$2:$B$17) -> 16
B22: Ringkasan Validasi Akuntansi
B24: Status | C24: Jumlah
B25: Setuju | C25: =COUNTIF('Validasi Akuntansi'!$G$2:$G$18,B25) -> 0
B26: Tidak Setuju | C26: =COUNTIF('Validasi Akuntansi'!$G$2:$G$18,B26) -> 0
B27: Perlu Diskusi | C27: =COUNTIF('Validasi Akuntansi'!$G$2:$G$18,B27) -> 0
B28: Belum diisi | C28: =COUNTA('Validasi Akuntansi'!$B$2:$B$18)-SUM(C25:C27) -> 17
B29: Total | C29: =COUNTA('Validasi Akuntansi'!$B$2:$B$18) -> 17
